kaleido/__init__.py
kaleido/scopes/__init__.py
kaleido/scopes/base.py
kaleido/scopes/plotly.py
kaleido/vendor/Mathjax-2.7.5.zip
kaleido/vendor/index.html
kaleido/vendor/kaleido_scopes.js
kaleido/vendor/mathjax/LICENSE
kaleido/vendor/mathjax/MathJax.js
kaleido/vendor/mathjax/README.md
kaleido/vendor/mathjax/latest.js
kaleido/vendor/mathjax/config/AM_CHTML-full.js
kaleido/vendor/mathjax/config/AM_CHTML.js
kaleido/vendor/mathjax/config/AM_HTMLorMML-full.js
kaleido/vendor/mathjax/config/AM_HTMLorMML.js
kaleido/vendor/mathjax/config/AM_SVG-full.js
kaleido/vendor/mathjax/config/AM_SVG.js
kaleido/vendor/mathjax/config/Accessible-full.js
kaleido/vendor/mathjax/config/Accessible.js
kaleido/vendor/mathjax/config/MML_CHTML-full.js
kaleido/vendor/mathjax/config/MML_CHTML.js
kaleido/vendor/mathjax/config/MML_HTMLorMML-full.js
kaleido/vendor/mathjax/config/MML_HTMLorMML.js
kaleido/vendor/mathjax/config/MML_SVG-full.js
kaleido/vendor/mathjax/config/MML_SVG.js
kaleido/vendor/mathjax/config/MMLorHTML.js
kaleido/vendor/mathjax/config/Safe.js
kaleido/vendor/mathjax/config/TeX-AMS-MML_HTMLorMML-full.js
kaleido/vendor/mathjax/config/TeX-AMS-MML_HTMLorMML.js
kaleido/vendor/mathjax/config/TeX-AMS-MML_SVG-full.js
kaleido/vendor/mathjax/config/TeX-AMS-MML_SVG.js
kaleido/vendor/mathjax/config/TeX-AMS_CHTML-full.js
kaleido/vendor/mathjax/config/TeX-AMS_CHTML.js
kaleido/vendor/mathjax/config/TeX-AMS_HTML-full.js
kaleido/vendor/mathjax/config/TeX-AMS_HTML.js
kaleido/vendor/mathjax/config/TeX-AMS_SVG-full.js
kaleido/vendor/mathjax/config/TeX-AMS_SVG.js
kaleido/vendor/mathjax/config/TeX-MML-AM_CHTML-full.js
kaleido/vendor/mathjax/config/TeX-MML-AM_CHTML.js
kaleido/vendor/mathjax/config/TeX-MML-AM_HTMLorMML-full.js
kaleido/vendor/mathjax/config/TeX-MML-AM_HTMLorMML.js
kaleido/vendor/mathjax/config/TeX-MML-AM_SVG-full.js
kaleido/vendor/mathjax/config/TeX-MML-AM_SVG.js
kaleido/vendor/mathjax/config/default.js
kaleido/vendor/mathjax/config/local/local.js
kaleido-0.4.2.dist-info/LICENSE.md
kaleido-0.4.2.dist-info/METADATA
kaleido-0.4.2.dist-info/WHEEL
kaleido-0.4.2.dist-info/top_level.txt
kaleido-0.4.2.dist-info/RECORD
