Metadata-Version: 2.1
Name: kaleido
Version: 0.4.2
Summary: Plotly graph export library
Author-email: Andrew Pikul <ajpikul@gmail.com>
Maintainer-email: Andrew Pikul <ajpikul@gmail.com>
License: The MIT License (MIT)
Requires-Python: >=3.9
License-File: LICENSE.md
Requires-Dist: choreographer>=0.99.6
Requires-Dist: async-timeout
Provides-Extra: dev
Requires-Dist: pytest; extra == "dev"
